README.md
setup.py
sner/__init__.py
sner/client.py
sner.egg-info/PKG-INFO
sner.egg-info/SOURCES.txt
sner.egg-info/dependency_links.txt
sner.egg-info/top_level.txt