Metadata-Version: 1.1
Name: sner
Version: 0.2.10
Summary: The Python interface to the Stanford Named Entity Recognizer Server.
Home-page: https://github.com/caihaoyu/sner
Author: caihaoyu
Author-email: chywj7@gmail.com
License: MIT
Keywords: python ner nlp stanford Named Entity Recognizer
Platform: UNKNOWN
Classifier: Development Status :: 3 - Alpha
Classifier: Intended Audience :: Developers
Classifier: Topic :: Software Development :: Build Tools
Classifier: License :: OSI Approved :: MIT License
Classifier: Programming Language :: Python :: 3
Classifier: Programming Language :: Python :: 3.5
Classifier: Programming Language :: Python :: 3.6
Classifier: Programming Language :: Python :: 3.7
